ligand_processor/__init__.py
ligand_processor/generate_top.py
ligand_processor/preprocess_mol2.py
ligand_processor-0.1.dist-info/LICENSE.txt
ligand_processor-0.1.dist-info/METADATA
ligand_processor-0.1.dist-info/WHEEL
ligand_processor-0.1.dist-info/entry_points.txt
ligand_processor-0.1.dist-info/top_level.txt
ligand_processor-0.1.dist-info/RECORD
